tkinter_page/__init__.py
tkinter_page-0.0.5.dist-info/LICENSE
tkinter_page-0.0.5.dist-info/METADATA
tkinter_page-0.0.5.dist-info/WHEEL
tkinter_page-0.0.5.dist-info/top_level.txt
tkinter_page-0.0.5.dist-info/RECORD
