Metadata-Version: 2.1
Name: tkinter_page
Version: 0.0.5
Summary: tkinter components extention
Home-page: https://github.com/CharlesShan-hub/tkinter_page
Author: Charles Shan
Author-email: charles.shht@gmail.com
License: UNKNOWN
Platform: UNKNOWN
Classifier: Programming Language :: Python :: 3
Classifier: License :: OSI Approved :: MIT License
Classifier: Operating System :: OS Independent
